aspy/__init__.py
aspy/yaml/__init__.py
aspy.yaml-1.2.0.dist-info/LICENSE
aspy.yaml-1.2.0.dist-info/METADATA
aspy.yaml-1.2.0.dist-info/WHEEL
aspy.yaml-1.2.0.dist-info/top_level.txt
aspy.yaml-1.2.0.dist-info/RECORD
