Metadata-Version: 2.1
Name: aspy.yaml
Version: 1.2.0
Summary: A few extensions to pyyaml.
Home-page: https://github.com/asottile/aspy.yaml
Author: Anthony Sottile
Author-email: asottile@umich.edu
License: MIT
Platform: all
Classifier: License :: OSI Approved :: MIT License
Classifier: Programming Language :: Python :: 2
Classifier: Programming Language :: Python :: 2.7
Classifier: Programming Language :: Python :: 3
Classifier: Programming Language :: Python :: 3.4
Classifier: Programming Language :: Python :: 3.5
Classifier: Programming Language :: Python :: 3.6
Classifier: Programming Language :: Python :: 3.7
Classifier: Programming Language :: Python :: Implementation :: PyPy
Requires-Python: >=2.7, !=3.0.*, !=3.1.*, !=3.2.*, !=3.3.*
